agentflow_cli/__init__.py
agentflow_cli/cli/__init__.py
agentflow_cli/cli/constants.py
agentflow_cli/cli/exceptions.py
agentflow_cli/cli/logger.py
agentflow_cli/cli/main.py
agentflow_cli/cli/commands/__init__.py
agentflow_cli/cli/commands/api.py
agentflow_cli/cli/commands/build.py
agentflow_cli/cli/commands/init.py
agentflow_cli/cli/commands/version.py
agentflow_cli/cli/core/__init__.py
agentflow_cli/cli/core/config.py
agentflow_cli/cli/core/output.py
agentflow_cli/cli/core/validation.py
agentflow_cli/cli/templates/__init__.py
agentflow_cli/cli/templates/defaults.py
agentflow_cli/src/__init__.py
agentflow_cli/src/app/__init__.py
agentflow_cli/src/app/loader.py
agentflow_cli/src/app/main.py
agentflow_cli/src/app/worker.py
agentflow_cli/src/app/core/__init__.py
agentflow_cli/src/app/core/auth/__init__.py
agentflow_cli/src/app/core/auth/auth_backend.py
agentflow_cli/src/app/core/auth/base_auth.py
agentflow_cli/src/app/core/auth/jwt_auth.py
agentflow_cli/src/app/core/config/__init__.py
agentflow_cli/src/app/core/config/graph_config.py
agentflow_cli/src/app/core/config/sentry_config.py
agentflow_cli/src/app/core/config/settings.py
agentflow_cli/src/app/core/config/setup_logs.py
agentflow_cli/src/app/core/config/setup_middleware.py
agentflow_cli/src/app/core/config/worker_middleware.py
agentflow_cli/src/app/core/exceptions/__init__.py
agentflow_cli/src/app/core/exceptions/general_exception.py
agentflow_cli/src/app/core/exceptions/handle_errors.py
agentflow_cli/src/app/core/exceptions/resources_exceptions.py
agentflow_cli/src/app/core/exceptions/user_exception.py
agentflow_cli/src/app/routers/__init__.py
agentflow_cli/src/app/routers/setup_router.py
agentflow_cli/src/app/routers/checkpointer/__init__.py
agentflow_cli/src/app/routers/checkpointer/router.py
agentflow_cli/src/app/routers/checkpointer/schemas/__init__.py
agentflow_cli/src/app/routers/checkpointer/schemas/checkpointer_schemas.py
agentflow_cli/src/app/routers/checkpointer/services/__init__.py
10xscale_agentflow_cli-0.2.6.dist-info/METADATA
10xscale_agentflow_cli-0.2.6.dist-info/WHEEL
10xscale_agentflow_cli-0.2.6.dist-info/entry_points.txt
10xscale_agentflow_cli-0.2.6.dist-info/top_level.txt
10xscale_agentflow_cli-0.2.6.dist-info/RECORD
