Metadata-Version: 2.4
Name: 10xscale-agentflow-cli
Version: 0.2.6
Summary: CLI and API for 10xscale AgentFlow
Author-email: 10xscale <contact@10xscale.ai>
Maintainer-email: Shudipto Trafder <shudiptotrafder@gmail.com>
License: MIT
Project-URL: Homepage, https://github.com/10xHub/agentflow-cli
Project-URL: Repository, https://github.com/10xHub/agentflow-cli
Project-URL: Issues, https://github.com/10xHub/agentflow-cli/issues
Project-URL: Documentation, https://agentflow-cli.readthedocs.io/
Keywords: 10xscale AgentFlow,api,fastapi,cli,agentflow
Classifier: Development Status :: 4 - Beta
Classifier: Intended Audience :: Developers
Classifier: License :: OSI Approved :: MIT License
Classifier: Operating System :: OS Independent
Classifier: Programming Language :: Python :: 3
Classifier: Programming Language :: Python :: 3.12
Classifier: Programming Language :: Python :: 3.13
Classifier: Topic :: Software Development :: Libraries :: Python Modules
Classifier: Topic :: Internet :: WWW/HTTP :: HTTP Servers
Requires-Python: >=3.12
Requires-Dist: 10xscale-agentflow>=0.5.0
Requires-Dist: fastapi
Requires-Dist: gunicorn
Requires-Dist: orjson
Requires-Dist: python-multipart
Requires-Dist: pydantic
Requires-Dist: pydantic-settings
Requires-Dist: uvicorn
Requires-Dist: typer
Requires-Dist: python-dotenv
Requires-Dist: PyJWT
Provides-Extra: sentry
Requires-Dist: sentry-sdk>=2.10.0; extra == "sentry"
Provides-Extra: firebase
Requires-Dist: firebase-admin>=6.5.0; extra == "firebase"
Requires-Dist: oauth2client>=4.1.3; extra == "firebase"
Provides-Extra: snowflakekit
Requires-Dist: snowflakekit; extra == "snowflakekit"
Provides-Extra: redis
Requires-Dist: redis>=5.0.7; extra == "redis"
Provides-Extra: gcloud
Requires-Dist: google-cloud-logging; extra == "gcloud"
